MANIFEST.in
README.rst
setup.py
funniest/__init__.py
funniest/text.py
funniest_test1985.egg-info/PKG-INFO
funniest_test1985.egg-info/SOURCES.txt
funniest_test1985.egg-info/dependency_links.txt
funniest_test1985.egg-info/not-zip-safe
funniest_test1985.egg-info/requires.txt
funniest_test1985.egg-info/top_level.txt