Metadata-Version: 1.0
Name: funniest-test1985
Version: 0.1
Summary: The funniest joke in the world for learning
Home-page: https://github.com/gegham85/funniest_python_package
Author: Gegham Movses
Author-email: gegham.movses@gmail.com
License: MIT
Platform: UNKNOWN
